<?xml version="1.0" encoding="UTF-8"?>
<!DOCTYPE mapper
  PUBLIC "-//mybatis.org//DTD Mapper 3.0//EN"
  "http://mybatis.org/dtd/mybatis-3-mapper.dtd">

<mapper namespace="com.santabooks.novel.dao.face.NovelDao">
	
	<sql id="memberNameAndScore">
		(
			SELECT memberName FROM member WHERE novel.memberNo = memberNo
		) AS memberName,
		(
			SELECT round(avg(score), 1) FROM episode WHERE novelNo = novel.novelNo
		) AS score,
		( SELECT count(*) FROM score WHERE episodeNo IN (SELECT episodeNo FROM episode WHERE novel.novelNo = novelNo)
		) AS cntScore
	</sql>
	<sql id="memberName">
		(
			SELECT memberName FROM member WHERE novel.memberNo = memberNo
		) AS memberName
	</sql>
	<sql id="listCondition">
		<trim prefix="WHERE" prefixOverrides="AND">
			<choose>
				<when test="search != null and search != ''">
					<choose>
						<when test="searchNo == 2">
							AND (SELECT memberName FROM member WHERE novel.memberNo = memberNo) LIKE '%' || #{search} || '%'
						</when>
						<otherwise>
							AND title LIKE '%' || #{search} || '%'
						</otherwise>
					</choose>
				</when>
				<otherwise>
				<if test="category gt 0 and category lt 6">
					AND category = #{category}
				</if>
				<if test="tableName == 'episode'">
					AND novelNo = #{novelNo}
				</if>
				<if test="category == 6">
					AND memberNo = #{memberNo}
				</if>
				</otherwise>
			</choose>
		</trim>
	</sql>

	<!-- novel -->
	<select id="selectMyNovel" parameterType="com.santabooks.member.dto.Member" resultType="com.santabooks.novel.dto.Novel">
		select * from (
			select rownum rnum, B.* FROM (
				SELECT novel.*,
				<include refid="memberNameAndScore"></include>
				FROM novel WHERE memberNo = #{memberNo}
			) B ORDER BY rnum
		) BOARD WHERE rnum BETWEEN #{startNo} AND #{endNo}
	</select>
	
	<select id="selectMyNovelByFavorite" parameterType="com.santabooks.util.Paging" resultType="com.santabooks.novel.dto.Novel">
		select * from (
			select rownum rnum, B.* FROM (
					SELECT n.*,
                    (SELECT memberName FROM member WHERE memberNo = n.novelNo) AS memberName,
                    (SELECT round(avg(score), 1) FROM episode WHERE novelNo = n.novelNo) AS score
					FROM novel n INNER JOIN favorite f
					ON n.novelNo = f.novelNo
					WHERE n.memberNo = #{memberNo}
				) B ORDER BY rnum
		) BOARD WHERE rnum BETWEEN #{startNo} AND #{endNo}
				
	</select>

	<select id="selectCntList" resultType="int" parameterType="com.santabooks.util.Paging">
	<choose>
		<when test="tableName == 'favorite'">
			SELECT count(*) FROM novel n INNER JOIN favorite f
			ON n.novelNo = f.novelNo
			WHERE n.memberNo = #{memberNo}
		</when>
		<otherwise>
			SELECT count(*) FROM ${tableName}
			<include refid="listCondition"></include>
		</otherwise>
	</choose>
	</select>
	
	<select id="selectNovelList" resultType="com.santabooks.novel.dto.Novel" parameterType="com.santabooks.util.Paging">
		select * from (
			select rownum rnum, B.* FROM (
				select novel.*,
				<include refid="memberNameAndScore"></include>
				from novel
				<include refid="listCondition"></include>	
				order by novelNo desc
				) B ORDER BY rnum
		) BOARD WHERE rnum BETWEEN #{startNo} AND #{endNo}
	</select>
	
	<select id="selectNovelByNovelNo" parameterType="int" resultType="com.santabooks.novel.dto.Novel">
		SELECT novel.*, 
		<include refid="memberNameAndScore"></include>
		FROM novel WHERE novelNo = #{novelNo}
	</select>
	
	<select id="selectBestNovel" resultType="com.santabooks.novel.dto.Novel">
		SELECT * FROM (
		    SELECT novel.*, 
		    <include refid="memberNameAndScore"></include>
		    FROM novel
		    <if test="category gt 0 and category lt 6">
		        WHERE category = #{category}
		    </if>
		        ORDER BY score ASC
		) novel WHERE ROWNUM BETWEEN 1 AND 3 ORDER BY novel.score ASC
	</select>
	
	<insert id="insertNovel" parameterType="com.santabooks.novel.dto.Novel">
		<selectKey order="BEFORE" keyColumn="novelNo" keyProperty="novelNo" resultType="int">
		SELECT novel_seq.nextval AS novelNo FROM dual
		</selectKey>
		INSERT INTO novel (novelNo, memberNo, title, discription, category)
					VALUES (#{novelNo}, #{memberNo}, #{title}, #{discription}, #{category})
	</insert>
	
	<update id="updateNovel" parameterType="com.santabooks.novel.dto.Novel">
		UPDATE novel SET title = #{title}, discription = #{discription}, category = #{category} WHERE novelNo = #{novelNo}
	</update>
	<update id="updateNovelImg" parameterType="com.santabooks.novel.dto.Novel">
		UPDATE novel SET imgOriginName = #{imgOriginName}, imgStoredName = #{imgStoredName} WHERE novelNo = #{novelNo}
	</update>
	
	<delete id="deleteNovel" parameterType="com.santabooks.novel.dto.Novel">
		DELETE FROM novel WHERE novelNo = #{novelNo}
	</delete>
	
	<!-- episode -->
	<select id="selectEpisodeByNovelNo" resultType="com.santabooks.novel.dto.Episode" parameterType="com.santabooks.util.Paging">
     	SELECT * FROM (
			SELECT rownum rnum, B.* FROM (
				SELECT * FROM episode WHERE novelNo = #{novelNo} ORDER BY episodeNo DESC
			) B ORDER BY rnum
		) BOARD WHERE rnum BETWEEN #{startNo} AND #{endNo}
		
	</select>
	
	<select id="selectEpisodeByEpisodeNo" resultType="com.santabooks.novel.dto.Episode" parameterType="com.santabooks.novel.dto.Episode">
		SELECT episode.*,
		(SELECT count(*) FROM score WHERE episode.episodeNo = episodeNo) AS cntScore
		FROM episode WHERE episodeNo = #{episodeNo}
	</select>
	
	<insert id="insertEpisode" parameterType="com.santabooks.novel.dto.Episode">
		<selectKey order="BEFORE" keyColumn="episodeNo" keyProperty="episodeNo" resultType="int">
			SELECT episode_seq.nextval AS episodeNo FROM dual
		</selectKey>
		
		INSERT INTO episode (episodeNo, novelNo, title, content, score)
					VALUES (#{episodeNo}, #{novelNo}, #{title}, #{content}, 
						(SELECT round(avg(score), 1) FROM score WHERE episodeNo = #{episodeNo} )
					)
	</insert>
	
	<update id="updateEpisode" parameterType="com.santabooks.novel.dto.Episode">
		UPDATE episode SET title = #{title}, content = #{content} WHERE episodeNo = #{episodeNo}
	</update>
	<delete id="deleteEpisode" parameterType="com.santabooks.novel.dto.Episode">
		DELETE FROM episode WHERE episodeNo = #{episodeNo}
	</delete>
	<update id="updateEpisodeScore" parameterType="com.santabooks.novel.dto.Score">
		UPDATE episode SET score = (SELECT round(avg(score), 1) FROM score WHERE episodeNo = episode.episodeNo) WHERE episodeNo = #{episodeNo}
	</update>

	<!-- score -->
	<select id="selectCntScoreByMemberNo" parameterType="com.santabooks.novel.dto.Score" resultType="int">
		SELECT count(*) FROM score WHERE episodeNo = #{episodeNo} AND memberNo = #{memberNo}
	</select>
	<select id="selectScoreByMemberNo" parameterType="com.santabooks.novel.dto.Score" resultType="com.santabooks.novel.dto.Score">
		SELECT * FROM score WHERE episodeNo = #{episodeNo} AND memberNo = #{memberNo}
	</select>
	
	<select id="selectScore" parameterType="com.santabooks.novel.dto.Score" resultType="com.santabooks.novel.dto.Score">
		SELECT
		round(avg(score), 1) score,
		count(*) cntScore
		FROM score WHERE episodeNo = #{episodeNo}
	</select>
	<insert id="insertScore" parameterType="com.santabooks.novel.dto.Score">
		INSERT INTO score VALUES (#{memberNo}, #{episodeNo}, #{score})
	</insert>
	<update id="updateScore" parameterType="com.santabooks.novel.dto.Score">
		UPDATE score SET score = #{score} WHERE episodeNo = #{episodeNo} AND memberNo = #{memberNo}
	</update>
	<delete id="deleteScore" parameterType="com.santabooks.novel.dto.Score">
		DELETE FROM score WHERE episodeNo = #{episodeNo} AND memberNo = #{memberNo}
	</delete>
	
	
	<!-- 즐겨찾기 -->
	<select id="selectCntFavorite" parameterType="com.santabooks.novel.dto.Favorite" resultType="int">
		SELECT COUNT(*) FROM favorite WHERE novelNo = #{novelNo}
	</select>
	<select id="selectCntFavoriteByMemberNo" parameterType="com.santabooks.novel.dto.Favorite" resultType="int">
		SELECT COUNT(*) FROM favorite WHERE memberNo = #{memberNo} AND novelNo = #{novelNo}
	</select>
	<insert id="insertFavorite" parameterType="com.santabooks.novel.dto.Favorite">
		INSERT INTO favorite VALUES (#{memberNo}, #{novelNo})
	</insert>
	<delete id="deleteFavorite" parameterType="com.santabooks.novel.dto.Favorite">
		DELETE FROM favorite WHERE memberNo = #{memberNo} AND novelNo = #{novelNo}
	</delete>

	<!-- 댓글 -->
	<select id="selectComment" parameterType="com.santabooks.novel.dto.Comment" resultType="com.santabooks.novel.dto.Comment">
		SELECT comment_table.*,
		(SELECT memberName FROM member WHERE memberNo = comment_table.memberNo) AS memberName
		FROM comment_table WHERE episodeNo = #{episodeNo}
		AND parentCmtNo = 0
		ORDER BY DECODE(parentCmtNo, 0, commentNo, parentCmtNo), seq
	</select>
	<select id="selectReply" parameterType="com.santabooks.novel.dto.Comment" resultType="com.santabooks.novel.dto.Comment">
		SELECT comment_table.*,
		(SELECT memberName FROM member WHERE memberNo = comment_table.memberNo) AS memberName
 		FROM comment_table
		WHERE episodeNo = #{episodeNo}
		AND parentCmtNo != 0
		AND commentNo = #{commentNo}
		ORDER BY DECODE(parentCmtNo, 0, commentNo, parentCmtNo), seq
	</select>
	
	<insert id="">
		INSERT INTO comment_table
		(commentNo, episodeNo, memberNo, content, parentCmtNo, seq)
		VALUES (#{commentNo}, #{episodeNo}, #{memberNo}, #{content}, #{parentCmtNo}, #{seq})
	</insert>

</mapper>
